mcp_wechat/__init__.py
mcp_wechat/__main__.py
mcp_wechat/server.py
mcp_wechat-0.1.1.dist-info/METADATA
mcp_wechat-0.1.1.dist-info/WHEEL
mcp_wechat-0.1.1.dist-info/top_level.txt
mcp_wechat-0.1.1.dist-info/RECORD
