Metadata-Version: 2.4
Name: mcp-wechat
Version: 0.1.1
Summary: 微信小助手，发送文本信息或文件给指定的群或者个人。example:发送今天是个好日子给文件传输助手
Requires-Python: >=3.10
Requires-Dist: annotated-types==0.7.0
Requires-Dist: anyio==4.9.0
Requires-Dist: certifi==2025.1.31
Requires-Dist: click==8.1.8
Requires-Dist: colorama==0.4.6
Requires-Dist: comtypes==1.4.10
Requires-Dist: h11==0.14.0
Requires-Dist: httpcore==1.0.7
Requires-Dist: httpx==0.28.1
Requires-Dist: httpx-sse==0.4.0
Requires-Dist: idna==3.10
Requires-Dist: mcp==1.5.0
Requires-Dist: pillow==11.1.0
Requires-Dist: psutil==7.0.0
Requires-Dist: pydantic==2.10.6
Requires-Dist: pydantic-core==2.27.2
Requires-Dist: pydantic-settings==2.8.1
Requires-Dist: pyperclip==1.9.0
Requires-Dist: python-dotenv==1.0.1
Requires-Dist: pywin32==310
Requires-Dist: sniffio==1.3.1
Requires-Dist: sse-starlette==2.2.1
Requires-Dist: starlette==0.46.1
Requires-Dist: typing-extensions==4.12.2
Requires-Dist: uvicorn==0.34.0
Requires-Dist: wxauto==3.9.11.17.5
